flask_imagekit/__init__.py
flask_imagekit/optimizer.py
flask_imagekit-1.0.3.dist-info/licenses/LICENSE
flask_imagekit-1.0.3.dist-info/METADATA
flask_imagekit-1.0.3.dist-info/WHEEL
flask_imagekit-1.0.3.dist-info/top_level.txt
flask_imagekit-1.0.3.dist-info/RECORD
